ruff_cgx/__init__.py
ruff_cgx/__main__.py
ruff_cgx/formatter.py
ruff_cgx/linter.py
ruff_cgx/template_formatter.py
ruff_cgx/utils.py
ruff_cgx-0.2.3.dist-info/licenses/LICENSE
ruff_cgx-0.2.3.dist-info/METADATA
ruff_cgx-0.2.3.dist-info/WHEEL
ruff_cgx-0.2.3.dist-info/entry_points.txt
ruff_cgx-0.2.3.dist-info/top_level.txt
ruff_cgx-0.2.3.dist-info/RECORD
