Metadata-Version: 2.4
Name: ruff-cgx
Version: 0.2.3
Summary: Ruff linter and formatter for collagraph single-file components
Author-email: Berend Klein Haneveld <berendkleinhaneveld@gmail.com>
License-Expression: MIT
Requires-Python: >=3.10
License-File: LICENSE
Requires-Dist: collagraph>=0.8.0
Requires-Dist: ruff
Dynamic: license-file
